make_resume/__init__.py
make_resume/make_resume.py
make_resume/template.html
make_resume-0.0.18.dist-info/METADATA
make_resume-0.0.18.dist-info/WHEEL
make_resume-0.0.18.dist-info/entry_points.txt
make_resume-0.0.18.dist-info/licenses/LICENSE
make_resume-0.0.18.dist-info/RECORD
