Metadata-Version: 2.3
Name: make-resume
Version: 0.0.18
Summary: YAML to HTML resume converter
Project-URL: Homepage, https://github.com/d3987ef8/make-resume
Project-URL: Issues, https://github.com/d3987ef8/make-resume/issues
Author-email: Jack Murray <contact@jackmurray.com>
License-File: LICENSE
Classifier: License :: OSI Approved :: MIT License
Classifier: Operating System :: OS Independent
Classifier: Programming Language :: Python :: 3
Requires-Python: >=3.8
Requires-Dist: jinja2
Requires-Dist: pyyaml
